schemax_openapi/__init__.py
schemax_openapi/_data_collector.py
schemax_openapi/_openapi_normalizer.py
schemax_openapi/py.typed
schemax_openapi-0.1.0.dist-info/METADATA
schemax_openapi-0.1.0.dist-info/WHEEL
schemax_openapi-0.1.0.dist-info/top_level.txt
schemax_openapi-0.1.0.dist-info/RECORD
