Metadata-Version: 2.1
Name: schemax-openapi
Version: 0.1.0
Summary: Useful OpenAPI parser for d42 universe
Home-page: https://github.com/Lolimpo/schemax-openapi
Author: Nikita Mikheev
Author-email: thelol1mpo@gmail.com
Classifier: License :: OSI Approved :: Apache Software License
Classifier: Programming Language :: Python :: 3.10
Classifier: Programming Language :: Python :: 3.11
Classifier: Programming Language :: Python :: 3.12
Classifier: Programming Language :: Python :: 3.13
Classifier: Typing :: Typed
Requires-Python: >=3.10
Requires-Dist: schemax<2.0.0,>=1.0.0
